pytech/sqlalchemy_tools/__init__.py
pytech/sqlalchemy_tools/deadlock.py
pytech/sqlalchemy_tools/logger.py
pytech/sqlalchemy_tools/models.py
pytech/sqlalchemy_tools/services/__init__.py
pytech/sqlalchemy_tools/services/build.py
pytech/sqlalchemy_tools/services/retrieve.py
pytech_sqlalchemy_tools-2.2.6.dist-info/METADATA
pytech_sqlalchemy_tools-2.2.6.dist-info/WHEEL
pytech_sqlalchemy_tools-2.2.6.dist-info/licenses/LICENCE
pytech_sqlalchemy_tools-2.2.6.dist-info/RECORD
